pah_core/__init__.py
pah_core/pah.py
pah_core/py.typed
pah_core/models/__init__.py
pah_core/models/highlight.py
pah_core/services/llm.py
pah_core/services/pdf.py
pah_core-1.3.2.dist-info/METADATA
pah_core-1.3.2.dist-info/WHEEL
pah_core-1.3.2.dist-info/RECORD
