Metadata-Version: 2.4
Name: pah-core
Version: 1.3.2
Requires-Dist: litellm>=1.71.2
Requires-Dist: pydantic>=2.11.5
Requires-Dist: pymupdf>=1.26.0
